README.rst
setup.py
backports/__init__.py
backports.ssl.egg-info/PKG-INFO
backports.ssl.egg-info/SOURCES.txt
backports.ssl.egg-info/dependency_links.txt
backports.ssl.egg-info/top_level.txt
backports/ssl/__init__.py
backports/ssl/core.py
backports/ssl/monkey.py
backports/ssl/subject_alt_name.py